src/PassKeeperStudent/student.py
passkeeperstudent-0.0.1.dist-info/METADATA
passkeeperstudent-0.0.1.dist-info/WHEEL
passkeeperstudent-0.0.1.dist-info/licenses/LICENSE
passkeeperstudent-0.0.1.dist-info/RECORD
