Metadata-Version: 2.1
Name: PassKeeperStudent
Version: 0.0.1
Summary: A student class with some project specific functions and classes
Author-email: Matt Bay <MJBayUNL@yahoo.com>
License-File: LICENSE
Classifier: License :: OSI Approved :: MIT License
Classifier: Operating System :: OS Independent
Classifier: Programming Language :: Python :: 3
Requires-Python: >=3.7
